JingtongNumpyShuzhiFenxiChuyi/README.md
JingtongNumpyShuzhiFenxiChuyi/__init__.py
JingtongNumpyShuzhiFenxiChuyi/__main__.py
JingtongNumpyShuzhiFenxiChuyi/file.epub
JingtongNumpyShuzhiFenxiChuyi/index.html
JingtongNumpyShuzhiFenxiChuyi/css/__init__.py
JingtongNumpyShuzhiFenxiChuyi/css/annotations.css
JingtongNumpyShuzhiFenxiChuyi/css/main.css
JingtongNumpyShuzhiFenxiChuyi/css/normalize.css
JingtongNumpyShuzhiFenxiChuyi/css/popup.css
JingtongNumpyShuzhiFenxiChuyi/font/__init__.py
JingtongNumpyShuzhiFenxiChuyi/font/fontello.eot
JingtongNumpyShuzhiFenxiChuyi/font/fontello.svg
JingtongNumpyShuzhiFenxiChuyi/font/fontello.ttf
JingtongNumpyShuzhiFenxiChuyi/font/fontello.woff
JingtongNumpyShuzhiFenxiChuyi/img/__init__.py
JingtongNumpyShuzhiFenxiChuyi/img/annotator-glyph-sprite.png
JingtongNumpyShuzhiFenxiChuyi/img/annotator-icon-sprite.png
JingtongNumpyShuzhiFenxiChuyi/img/apple-touch-icon.png
JingtongNumpyShuzhiFenxiChuyi/img/cancelfullscreen.png
JingtongNumpyShuzhiFenxiChuyi/img/close.png
JingtongNumpyShuzhiFenxiChuyi/img/fullscreen.png
JingtongNumpyShuzhiFenxiChuyi/img/loader.gif
JingtongNumpyShuzhiFenxiChuyi/img/menu-icon.png
JingtongNumpyShuzhiFenxiChuyi/img/save.png
JingtongNumpyShuzhiFenxiChuyi/img/saved.png
JingtongNumpyShuzhiFenxiChuyi/img/settings-s.png
JingtongNumpyShuzhiFenxiChuyi/img/settings.png
JingtongNumpyShuzhiFenxiChuyi/img/star.png
JingtongNumpyShuzhiFenxiChuyi/js/__init__.py
JingtongNumpyShuzhiFenxiChuyi/js/epub.js
JingtongNumpyShuzhiFenxiChuyi/js/epub.min.js
JingtongNumpyShuzhiFenxiChuyi/js/epub.min.map
JingtongNumpyShuzhiFenxiChuyi/js/hooks.min.js
JingtongNumpyShuzhiFenxiChuyi/js/hooks.min.map
JingtongNumpyShuzhiFenxiChuyi/js/reader.js
JingtongNumpyShuzhiFenxiChuyi/js/reader.js.map
JingtongNumpyShuzhiFenxiChuyi/js/reader.min.js
JingtongNumpyShuzhiFenxiChuyi/js/reader.min.map
JingtongNumpyShuzhiFenxiChuyi/js/hooks/__init__.py
JingtongNumpyShuzhiFenxiChuyi/js/hooks/extensions/__init__.py
JingtongNumpyShuzhiFenxiChuyi/js/hooks/extensions/highlight.js
jingtong_numpy_shuzhi_fenxi_chuyi-2024.3.4.0.dist-info/METADATA
jingtong_numpy_shuzhi_fenxi_chuyi-2024.3.4.0.dist-info/WHEEL
jingtong_numpy_shuzhi_fenxi_chuyi-2024.3.4.0.dist-info/entry_points.txt
jingtong_numpy_shuzhi_fenxi_chuyi-2024.3.4.0.dist-info/top_level.txt
jingtong_numpy_shuzhi_fenxi_chuyi-2024.3.4.0.dist-info/RECORD
